bugscanner/__init__.py
bugscanner/__main__.py
bugscanner/bug_scanner.py
bugscanner/direct_scanner.py
bugscanner/proxy_scanner.py
bugscanner/ssl_scanner.py
bugscanner/udp_scanner.py
bugscanner-0.1.8.dist-info/LICENSE
bugscanner-0.1.8.dist-info/METADATA
bugscanner-0.1.8.dist-info/WHEEL
bugscanner-0.1.8.dist-info/entry_points.txt
bugscanner-0.1.8.dist-info/top_level.txt
bugscanner-0.1.8.dist-info/RECORD
