Metadata-Version: 2.1
Name: bugscanner
Version: 0.1.8
Summary: Bug Scanner for Internet Freedom (Domain Fronting, Server Name Indication, Etc)
Home-page: https://github.com/aztecrabbit/bugscanner
Author: aztecrabbit
Author-email: ars.xda@gmail.com
License: UNKNOWN
Platform: UNKNOWN
Classifier: Programming Language :: Python :: 3
Classifier: License :: OSI Approved :: MIT License
Classifier: Operating System :: OS Independent
Requires-Python: >=3.6
